dnplans/__init__.py
dnplans/admin.py
dnplans/apps.py
dnplans/conf.py
dnplans/context_processors.py
dnplans/contrib.py
dnplans/enum.py
dnplans/forms.py
dnplans/importer.py
dnplans/listeners.py
dnplans/mixins.py
dnplans/models.py
dnplans/plan_change.py
dnplans/quota.py
dnplans/signals.py
dnplans/tasks.py
dnplans/urls.py
dnplans/validators.py
dnplans/views.py
dnplans/management/__init__.py
dnplans/management/commands/__init__.py
dnplans/management/commands/create_userplans.py
dnplans/migrations/0001_initial.py
dnplans/migrations/0002_auto_20180901_1744.py
dnplans/migrations/0003_make_plans_unique.py
dnplans/migrations/0004_create_user_plans.py
dnplans/migrations/0005_auto_20190403_1231.py
dnplans/migrations/__init__.py
dnplans/taxation/__init__.py
dnplans/taxation/eu.py
dnplans/taxation/ru.py
dnplans/templates/mail/change_plan_body.txt
dnplans/templates/mail/change_plan_title.txt
dnplans/templates/mail/expired_account_body.txt
dnplans/templates/mail/expired_account_title.txt
dnplans/templates/mail/extend_account_body.txt
dnplans/templates/mail/extend_account_title.txt
dnplans/templates/mail/invoice_created_body.txt
dnplans/templates/mail/invoice_created_title.txt
dnplans/templates/mail/remind_expire_body.txt
dnplans/templates/mail/remind_expire_title.txt
dnplans/templates/plans/account_activation.html
dnplans/templates/plans/base.html
dnplans/templates/plans/billing_info_create.html
dnplans/templates/plans/billing_info_delete.html
dnplans/templates/plans/billing_info_update.html
dnplans/templates/plans/create_order.html
dnplans/templates/plans/current.html
dnplans/templates/plans/expiration_messages.html
dnplans/templates/plans/extend.html
dnplans/templates/plans/fake_payments.html
dnplans/templates/plans/order_detail.html
dnplans/templates/plans/order_detail_table.html
dnplans/templates/plans/order_list.html
dnplans/templates/plans/pagination.html
dnplans/templates/plans/plan_table.html
dnplans/templates/plans/pricing.html
dnplans/templates/plans/upgrade.html
dn_plans-0.1.dist-info/LICENSE
dn_plans-0.1.dist-info/METADATA
dn_plans-0.1.dist-info/WHEEL
dn_plans-0.1.dist-info/top_level.txt
dn_plans-0.1.dist-info/RECORD
